README.md
setup.py
qiwi_bills/__init__.py
qiwi_bills/kassa.py
qiwi_bills.egg-info/PKG-INFO
qiwi_bills.egg-info/SOURCES.txt
qiwi_bills.egg-info/dependency_links.txt
qiwi_bills.egg-info/requires.txt
qiwi_bills.egg-info/top_level.txt