Metadata-Version: 1.0
Name: qiwi-bills
Version: 0.1
Summary: Qiwi API client
Home-page: https://github.com/adilkhash/qiwi
Author: Adylzhan Khashtamov
Author-email: adil.khashtamov@gmail.com
License: MIT
Platform: UNKNOWN
